growatt_pico_reader/__init__.py
growatt_pico_reader/growatt_pico_reader.py
growatt_pico_reader-0.1.3.dist-info/METADATA
growatt_pico_reader-0.1.3.dist-info/WHEEL
growatt_pico_reader-0.1.3.dist-info/licenses/LICENSE.md
growatt_pico_reader-0.1.3.dist-info/RECORD
