Metadata-Version: 2.4
Name: growatt_pico_reader
Version: 0.1.3
Summary: A tool for reading Growatt inverter data on Raspberry Pi Pico
Project-URL: Homepage, https://github.com/TTLES33/growatt_pico_reader
Project-URL: Repository, https://github.com/TTLES33/growatt_pico_reader.git
Project-URL: Issues, https://github.com/TTLES33/growatt_pico_reader/issues
Author-email: Jan TTLES Grygar <ttles33@gmail.com>
License-Expression: MIT
License-File: LICENSE.md
Keywords: growatt,photovoltaic,pico,pico w,raspberry
Classifier: License :: OSI Approved :: MIT License
Classifier: Operating System :: OS Independent
Classifier: Programming Language :: Python :: 3
Requires-Python: >=3.7
